pyracmon/__init__.py
pyracmon/batch.py
pyracmon/clause.py
pyracmon/config.py
pyracmon/connection.py
pyracmon/context.py
pyracmon/dbapi.py
pyracmon/marker.py
pyracmon/mixin.py
pyracmon/model.py
pyracmon/model_graph.py
pyracmon/query.py
pyracmon/query_graph.py
pyracmon/select.py
pyracmon/sql.py
pyracmon/stub.py
pyracmon/util.py
pyracmon/dialect/__init__.py
pyracmon/dialect/mysql.py
pyracmon/dialect/postgresql.py
pyracmon/dialect/shared.py
pyracmon/graph/__init__.py
pyracmon/graph/graph.py
pyracmon/graph/identify.py
pyracmon/graph/protocol.py
pyracmon/graph/schema.py
pyracmon/graph/serialize.py
pyracmon/graph/spec.py
pyracmon/graph/stub.py
pyracmon/graph/template.py
pyracmon/graph/typing.py
pyracmon/testing/__init__.py
pyracmon/testing/model.py
pyracmon/testing/util.py
pyracmon-1.0.1.dist-info/METADATA
pyracmon-1.0.1.dist-info/WHEEL
pyracmon-1.0.1.dist-info/licenses/LICENSE
pyracmon-1.0.1.dist-info/RECORD
