Metadata-Version: 2.4
Name: pyracmon
Version: 1.0.1
Summary: Python O/R Mapping extension for DB-API 2.0
Project-URL: Homepage, https://github.com/sozu/py-pyracmon
Author-email: sozuberry <sozuberry@gmail.com>
License-File: LICENSE
Classifier: License :: OSI Approved :: MIT License
Classifier: Operating System :: OS Independent
Classifier: Programming Language :: Python :: 3.9
Requires-Python: >=3.9
Requires-Dist: typing-extensions
